melinda/__init__.py
melinda/metrics/__init__.py
melinda/metrics/classification.py
melinda/metrics/test_stand.py
melinda/models/__init__.py
melinda/models/tabular.py
melinda/models/utils.py
melinda-0.1.1.dist-info/LICENSE
melinda-0.1.1.dist-info/METADATA
melinda-0.1.1.dist-info/WHEEL
melinda-0.1.1.dist-info/RECORD
