Metadata-Version: 2.1
Name: melinda
Version: 0.1.1
Summary: Synthetic data generation.
Home-page: https://github.com/HSE-LAMBDA/LINDA
License: MIT
Keywords: synthetic data,augmentation,generative models,tabular data
Author: Mikhail Hushchyn
Author-email: hushchyn.mikhail@gmail.com
Requires-Python: >=3.8,<4.0
Classifier: License :: OSI Approved :: MIT License
Classifier: Programming Language :: Python :: 3
Classifier: Programming Language :: Python :: 3.8
Classifier: Programming Language :: Python :: 3.9
Classifier: Programming Language :: Python :: 3.10
Classifier: Programming Language :: Python :: 3.11
Classifier: Programming Language :: Python :: 3.12
Requires-Dist: jupyterlab (==4.0.5)
Requires-Dist: kaleido (==0.2.1)
Requires-Dist: plotly (==5.16.1)
Requires-Dist: probaforms (==0.2.0)
Requires-Dist: scikit-learn (==1.3.0)
Requires-Dist: sdmetrics (==0.11.0)
Project-URL: Repository, https://github.com/HSE-LAMBDA/LINDA
